{
  "00:00": "test.mp4",
  "00:05": "test2.mp4",
  "00:10": "test.mp4",
  "00:15": "test2.mp4",
  "00:20": "test.mp4",
  "00:25": "test2.mp4",
  "00:30": "ultimatesounds_s1_e1.mp4",
  "00:35": "test2.mp4",
  "00:40": "test.mp4",
  "00:45": "test2.mp4",
  "00:50": "test.mp4",
  "00:55": "test2.mp4",
  "01:00": "test.mp4",
  "01:05": "test2.mp4",
  "01:10": "test.mp4",
  "01:15": "test2.mp4",
  "01:20": "test.mp4",
  "01:25": "test2.mp4",
  "01:30": "test.mp4",
  "01:35": "test2.mp4",
  "01:40": "test.mp4",
  "01:45": "test2.mp4",
  "01:50": "test.mp4",
  "01:55": "test2.mp4",
  "02:00": "test.mp4",
  "02:05": "test2.mp4",
  "02:10": "test.mp4",
  "02:15": "test2.mp4",
  "02:20": "test.mp4",
  "02:25": "test2.mp4",
  "02:30": "ultimatesounds_s1_e1.mp4",
  "02:35": "test2.mp4",
  "02:40": "test.mp4",
  "02:45": "test2.mp4",
  "02:50": "test.mp4",
  "02:55": "test2.mp4",
  "03:00": "test.mp4",
  "03:05": "test2.mp4",
  "03:10": "test.mp4",
  "03:15": "test2.mp4",
  "03:20": "test.mp4",
  "03:25": "test2.mp4",
  "03:30": "test.mp4",
  "03:35": "test2.mp4",
  "03:40": "test.mp4",
  "03:45": "test2.mp4",
  "03:50": "test.mp4",
  "03:55": "test2.mp4",
  "04:00": "test.mp4",
  "04:05": "test2.mp4",
  "04:10": "test.mp4",
  "04:15": "test2.mp4",
  "04:20": "test.mp4",
  "04:25": "test2.mp4",
  "04:30": "ultimatesounds_s1_e1.mp4",
  "04:35": "test2.mp4",
  "04:40": "test.mp4",
  "04:45": "test2.mp4",
  "04:50": "test.mp4",
  "04:55": "test2.mp4",
  "05:00": "test.mp4",
  "05:05": "test2.mp4",
  "05:10": "test.mp4",
  "05:15": "test2.mp4",
  "05:20": "test.mp4",
  "05:25": "test2.mp4",
  "05:30": "test.mp4",
  "05:35": "test2.mp4",
  "05:40": "test.mp4",
  "05:45": "test2.mp4",
  "05:50": "test.mp4",
  "05:55": "test2.mp4",
  "06:00": "test.mp4",
  "06:05": "test2.mp4",
  "06:10": "test.mp4",
  "06:15": "test2.mp4",
  "06:20": "test.mp4",
  "06:25": "test2.mp4",
  "06:30": "ultimatesounds_s1_e1.mp4",
  "06:35": "test2.mp4",
  "06:40": "test.mp4",
  "06:45": "test2.mp4",
  "06:50": "test.mp4",
  "06:55": "test2.mp4",
  "07:00": "test.mp4",
  "07:05": "test2.mp4",
  "07:10": "test.mp4",
  "07:15": "test2.mp4",
  "07:20": "test.mp4",
  "07:25": "test2.mp4",
  "07:30": "test.mp4",
  "07:35": "test2.mp4",
  "07:40": "test.mp4",
  "07:45": "test2.mp4",
  "07:50": "test.mp4",
  "07:55": "test2.mp4",
  "08:00": "test.mp4",
  "08:05": "test2.mp4",
  "08:10": "test.mp4",
  "08:15": "test2.mp4",
  "08:20": "test.mp4",
  "08:25": "test2.mp4",
  "08:30": "ultimatesounds_s1_e1.mp4",
  "08:35": "test2.mp4",
  "08:40": "test.mp4",
  "08:45": "test2.mp4",
  "08:50": "test.mp4",
  "08:55": "test2.mp4",
  "09:00": "test.mp4",
  "09:05": "test2.mp4",
  "09:10": "test.mp4",
  "09:15": "test2.mp4",
  "09:20": "test.mp4",
  "09:25": "test2.mp4",
  "09:30": "test.mp4",
  "09:35": "test2.mp4",
  "09:40": "test.mp4",
  "09:45": "test2.mp4",
  "09:50": "test.mp4",
  "09:55": "test2.mp4",
  "10:00": "test.mp4",
  "10:05": "test2.mp4",
  "10:10": "test.mp4",
  "10:15": "test2.mp4",
  "10:20": "test.mp4",
  "10:25": "test2.mp4",
  "10:30": "ultimatesounds_s1_e1.mp4",
  "10:35": "test2.mp4",
  "10:40": "test.mp4",
  "10:45": "test2.mp4",
  "10:50": "test.mp4",
  "10:55": "test2.mp4",
  "11:00": "test.mp4",
  "11:05": "test2.mp4",
  "11:10": "test.mp4",
  "11:15": "test2.mp4",
  "11:20": "test.mp4",
  "11:25": "test2.mp4",
  "11:30": "test.mp4",
  "11:35": "test2.mp4",
  "11:40": "test.mp4",
  "11:45": "test2.mp4",
  "11:50": "test.mp4",
  "11:55": "test2.mp4",
  "12:00": "test.mp4",
  "12:05": "test2.mp4",
  "12:10": "test.mp4",
  "12:15": "test2.mp4",
  "12:20": "test.mp4",
  "12:25": "test2.mp4",
  "12:30": "ultimatesounds_s1_e1.mp4",
  "12:35": "test2.mp4",
  "12:40": "test.mp4",
  "12:45": "test2.mp4",
  "12:50": "test.mp4",
  "12:55": "test2.mp4",
  "13:00": "test.mp4",
  "13:05": "test2.mp4",
  "13:10": "test.mp4",
  "13:15": "test2.mp4",
  "13:20": "test.mp4",
  "13:25": "test2.mp4",
  "13:30": "test.mp4",
  "13:35": "test2.mp4",
  "13:40": "test.mp4",
  "13:45": "test2.mp4",
  "13:50": "test.mp4",
  "13:55": "test2.mp4",
  "14:00": "test.mp4",
  "14:05": "test2.mp4",
  "14:10": "test.mp4",
  "14:15": "test2.mp4",
  "14:20": "test.mp4",
  "14:25": "test2.mp4",
  "14:30": "ultimatesounds_s1_e1.mp4",
  "14:35": "test2.mp4",
  "14:40": "test.mp4",
  "14:45": "test2.mp4",
  "14:50": "test.mp4",
  "14:55": "test2.mp4",
  "15:00": "test.mp4",
  "15:05": "test2.mp4",
  "15:10": "test.mp4",
  "15:15": "test2.mp4",
  "15:20": "test.mp4",
  "15:25": "test2.mp4",
  "15:30": "test.mp4",
  "15:35": "test2.mp4",
  "15:40": "test.mp4",
  "15:45": "test2.mp4",
  "15:50": "test.mp4",
  "15:55": "test2.mp4",
  "16:00": "test.mp4",
  "16:05": "test2.mp4",
  "16:10": "test.mp4",
  "16:15": "test2.mp4",
  "16:20": "test.mp4",
  "16:25": "test2.mp4",
  "16:30": "ultimatesounds_s1_e1.mp4",
  "16:35": "test2.mp4",
  "16:40": "test.mp4",
  "16:45": "test2.mp4",
  "16:50": "test.mp4",
  "16:55": "test2.mp4",
  "17:00": "test.mp4",
  "17:05": "test2.mp4",
  "17:10": "test.mp4",
  "17:15": "test2.mp4",
  "17:20": "test.mp4",
  "17:25": "test2.mp4",
  "17:30": "test.mp4",
  "17:35": "test2.mp4",
  "17:40": "test.mp4",
  "17:45": "test2.mp4",
  "17:50": "test.mp4",
  "17:55": "test2.mp4",
  "18:00": "test.mp4",
  "18:05": "test2.mp4",
  "18:10": "test.mp4",
  "18:15": "test2.mp4",
  "18:20": "test.mp4",
  "18:25": "test2.mp4",
  "18:30": "ultimatesounds_s1_e1.mp4",
  "18:35": "test2.mp4",
  "18:40": "test.mp4",
  "18:45": "test2.mp4",
  "18:50": "test.mp4",
  "18:55": "test2.mp4",
  "19:00": "test.mp4",
  "19:05": "test2.mp4",
  "19:10": "test.mp4",
  "19:15": "test2.mp4",
  "19:20": "test.mp4",
  "19:25": "test2.mp4",
  "19:30": "test.mp4",
  "19:35": "test2.mp4",
  "19:40": "test.mp4",
  "19:45": "test2.mp4",
  "19:50": "test.mp4",
  "19:55": "test2.mp4",
  "20:00": "test.mp4",
  "20:05": "test2.mp4",
  "20:10": "test.mp4",
  "20:15": "test2.mp4",
  "20:20": "test.mp4",
  "20:25": "test2.mp4",
  "20:30": "ultimatesounds_s1_e1.mp4",
  "20:35": "test2.mp4",
  "20:40": "test.mp4",
  "20:45": "test2.mp4",
  "20:50": "test.mp4",
  "20:55": "test2.mp4",
  "21:00": "test.mp4",
  "21:05": "test2.mp4",
  "21:10": "test.mp4",
  "21:15": "test2.mp4",
  "21:20": "test.mp4",
  "21:25": "test2.mp4",
  "21:30": "test.mp4",
  "21:35": "test2.mp4",
  "21:40": "test.mp4",
  "21:45": "test2.mp4",
  "21:50": "test.mp4",
  "21:55": "test2.mp4",
  "22:00": "test.mp4",
  "22:05": "test2.mp4",
  "22:10": "test.mp4",
  "22:15": "test2.mp4",
  "22:20": "test.mp4",
  "22:25": "test2.mp4",
  "22:30": "ultimatesounds_s1_e1.mp4",
  "22:35": "test2.mp4",
  "22:40": "test.mp4",
  "22:45": "test2.mp4",
  "22:50": "test.mp4",
  "22:55": "test2.mp4",
  "23:00": "test.mp4",
  "23:05": "test2.mp4",
  "23:10": "test.mp4",
  "23:15": "test2.mp4",
  "23:20": "test.mp4",
  "23:25": "test2.mp4",
  "23:30": "test.mp4",
  "23:35": "test2.mp4",
  "23:40": "test.mp4",
  "23:45": "test2.mp4",
  "23:50": "test.mp4",
  "23:55": "test2.mp4"
}
